COPYING
MANIFEST.in
README.rst
setup.cfg
setup.py
sphinx_server.egg-info/PKG-INFO
sphinx_server.egg-info/SOURCES.txt
sphinx_server.egg-info/dependency_links.txt
sphinx_server.egg-info/entry_points.txt
sphinx_server.egg-info/requires.txt
sphinx_server.egg-info/top_level.txt
sphinxserver/__init__.py
sphinxserver/_app.py
tests/__init__.py
tests/__init__.pyc
tests/test_app.py