Metadata-Version: 1.1
Name: sphinx-server
Version: 0.1.0
Summary: simple wsgi spinx server
Home-page: https://github.com/rmohr/sphinx-server
Author: Roman Mohr
Author-email: roman@fenkhuber.at
License: UNKNOWN
Keywords: wsgi sphinx documentation server webapps
Platform: UNKNOWN
Classifier: Development Status :: 4 - Beta
Classifier: Environment :: Web Environment
Classifier: Intended Audience :: Developers
Classifier: License :: OSI Approved :: GNU General Public License v3 (GPLv3)
Classifier: Natural Language :: English
Classifier: Operating System :: OS Independent
Classifier: Programming Language :: Python
Classifier: Topic :: Software Development :: Documentation
Classifier: Topic :: Utilities
